odoo/addons/ssi_fixed_asset_qrcode/README.rst
odoo/addons/ssi_fixed_asset_qrcode/__init__.py
odoo/addons/ssi_fixed_asset_qrcode/__manifest__.py
odoo/addons/ssi_fixed_asset_qrcode/i18n/id.po
odoo/addons/ssi_fixed_asset_qrcode/i18n/ssi_fixed_asset_qrcode.pot
odoo/addons/ssi_fixed_asset_qrcode/models/__init__.py
odoo/addons/ssi_fixed_asset_qrcode/models/fixed_asset_asset.py
odoo/addons/ssi_fixed_asset_qrcode/static/description/icon.png
odoo14_addon_ssi_fixed_asset_qrcode-14.0.1.2.0.dist-info/METADATA
odoo14_addon_ssi_fixed_asset_qrcode-14.0.1.2.0.dist-info/WHEEL
odoo14_addon_ssi_fixed_asset_qrcode-14.0.1.2.0.dist-info/top_level.txt
odoo14_addon_ssi_fixed_asset_qrcode-14.0.1.2.0.dist-info/RECORD
